multi_function/WordCloud.py
multi_function/__init__.py
multi_function/bot.py
multi_function/get_music.py
multi_function/pinyin.py
multi_function/qr.py
multi_function/requests_download.py
multi_function/send_email.py
multi_function/translate.py
fmz-2.2.0.dist-info/METADATA
fmz-2.2.0.dist-info/WHEEL
fmz-2.2.0.dist-info/top_level.txt
fmz-2.2.0.dist-info/RECORD
