Metadata-Version: 2.1
Name: fmz
Version: 2.2.0
Summary: UNKNOWN
Home-page: UNKNOWN
Author: fu-mingzhe
Author-email: 2372769798@qq.com
License: UNKNOWN
Platform: UNKNOWN
Classifier: Programming Language :: Python :: 3
Classifier: License :: OSI Approved :: MIT License
Classifier: Operating System :: OS Independent
Requires-Python: >=3.6.0
Requires-Dist: easygui
Requires-Dist: jieba
Requires-Dist: numpy
Requires-Dist: pillow
Requires-Dist: pycryptodome
Requires-Dist: pypinyin
Requires-Dist: qrcode
Requires-Dist: requests
Requires-Dist: retrying
Requires-Dist: tqdm
Requires-Dist: wordcloud
